stepflow_py/__init__.py
stepflow_py/client.py
stepflow_py/py.typed
stepflow_py/api/__init__.py
stepflow_py/api/api_client.py
stepflow_py/api/api_response.py
stepflow_py/api/configuration.py
stepflow_py/api/exceptions.py
stepflow_py/api/py.typed
stepflow_py/api/rest.py
stepflow_py/api/api/__init__.py
stepflow_py/api/api/component_api.py
stepflow_py/api/api/flow_api.py
stepflow_py/api/api/health_api.py
stepflow_py/api/api/run_api.py
stepflow_py/api/models/__init__.py
stepflow_py/api/models/coalesce.py
stepflow_py/api/models/component_info.py
stepflow_py/api/models/create_run_request.py
stepflow_py/api/models/create_run_response.py
stepflow_py/api/models/diagnostic.py
stepflow_py/api/models/diagnostic_level.py
stepflow_py/api/models/diagnostics.py
stepflow_py/api/models/error_action.py
stepflow_py/api/models/example_input.py
stepflow_py/api/models/execution_status.py
stepflow_py/api/models/flow.py
stepflow_py/api/models/flow_error.py
stepflow_py/api/models/flow_response.py
stepflow_py/api/models/flow_result.py
stepflow_py/api/models/flow_result_failed.py
stepflow_py/api/models/flow_result_success.py
stepflow_py/api/models/flow_schema.py
stepflow_py/api/models/health_query.py
stepflow_py/api/models/health_response.py
stepflow_py/api/models/input_ref.py
stepflow_py/api/models/item_result.py
stepflow_py/api/models/item_statistics.py
stepflow_py/api/models/list_components_query.py
stepflow_py/api/models/list_components_response.py
stepflow_py/api/models/list_items_response.py
stepflow_py/api/models/list_runs_query.py
stepflow_py/api/models/list_runs_response.py
stepflow_py/api/models/list_step_runs_response.py
stepflow_py/api/models/literal_expr.py
stepflow_py/api/models/model_if.py
stepflow_py/api/models/on_error_default.py
stepflow_py/api/models/on_error_fail.py
stepflow_py/api/models/on_error_retry.py
stepflow_py/api/models/override_type.py
stepflow_py/api/models/primitive_value.py
stepflow_py/api/models/run_details.py
stepflow_py/api/models/run_flow_response.py
stepflow_py-0.9.2.dist-info/METADATA
stepflow_py-0.9.2.dist-info/WHEEL
stepflow_py-0.9.2.dist-info/entry_points.txt
stepflow_py-0.9.2.dist-info/RECORD
